README.md
setup.py
dj_oauth/__init__.py
dj_oauth/models.py
dj_oauth/serializers.py
dj_oauth/settings.py
dj_oauth/urls.py
dj_oauth/views.py
dj_oauth/authentication/__init__.py
dj_oauth/authentication/apple.py
dj_oauth/authentication/facebook.py
dj_oauth/authentication/google.py
dj_oauth/authentication/linkedin.py
dj_oauth/management/__init__.py
dj_oauth/management/groups.py
dj_oauth/management/roles.py
dj_oauth/management/scopes.py
ideal_dj_oauth2.egg-info/PKG-INFO
ideal_dj_oauth2.egg-info/SOURCES.txt
ideal_dj_oauth2.egg-info/dependency_links.txt
ideal_dj_oauth2.egg-info/requires.txt
ideal_dj_oauth2.egg-info/top_level.txt