Metadata-Version: 2.1
Name: ideal-dj-oauth2
Version: 0.1.0
Summary: A Django REST framework package for OAuth2.0 and social account management
Home-page: https://github.com/prashantidealittechno/dj-oauth
Author: Prashant IdealITTechno
Author-email: prashantidealittechno@gmail.com
Classifier: Programming Language :: Python :: 3
Classifier: License :: OSI Approved :: MIT License
Classifier: Operating System :: OS Independent
Requires-Python: >=3.6
